cutlery/__init__.py
cutlery/_bbpe.cp37-win_amd64.pyd
cutlery/_bbpe.cpp
cutlery/_bbpe.pxd
cutlery/_bbpe.pyx
cutlery/_spp.cp37-win_amd64.pyd
cutlery/_spp.cpp
cutlery/_spp.pxd
cutlery/_spp.pyx
cutlery/_wordpiece.cp37-win_amd64.pyd
cutlery/_wordpiece.cpp
cutlery/_wordpiece.pxd
cutlery/_wordpiece.pyx
cutlery/config.h
cutlery/merges.cc
cutlery/merges.hh
cutlery/util.hh
cutlery/wordpiece.cc
cutlery/wordpiece.hh
cutlery/tests/__init__.py
cutlery/tests/incorrect-merges.txt
cutlery/tests/robbert-merges-1000.txt
cutlery/tests/robbert-vocab-1000.json
cutlery/tests/test_bbpe_processor.py
cutlery/tests/test_sp.py
cutlery/tests/test_word_piece_processor.py
cutlery/tests/toy-word-pieces.txt
cutlery/tests/toy.model
cutlery-0.0.6.dist-info/LICENSE
cutlery-0.0.6.dist-info/METADATA
cutlery-0.0.6.dist-info/WHEEL
cutlery-0.0.6.dist-info/top_level.txt
cutlery-0.0.6.dist-info/zip-safe
cutlery-0.0.6.dist-info/RECORD
